{
    "staff": [
        {
            "id": "staff_1771694719342_f0i9f",
            "name": "松井",
            "type": "full",
            "nightShiftType": "all",
            "canOvertime": true,
            "earlyOnly": false,
            "lateOnly": false,
            "monthlyDaysOff": 9,
            "maxDaysPerWeek": 3,
            "maxConsecutive": 2,
            "startTime": "",
            "endTime": ""
        },
        {
            "id": "staff_1771694725701_ixn3o",
            "name": "坂井",
            "type": "full",
            "nightShiftType": "weekday",
            "canOvertime": true,
            "earlyOnly": false,
            "lateOnly": false,
            "monthlyDaysOff": 9,
            "maxDaysPerWeek": 3,
            "maxConsecutive": 2,
            "startTime": "",
            "endTime": ""
        },
        {
            "id": "staff_1771701050833_55q61",
            "name": "田中",
            "type": "full",
            "nightShiftType": "all",
            "canOvertime": true,
            "earlyOnly": false,
            "lateOnly": false,
            "monthlyDaysOff": 9,
            "maxDaysPerWeek": 3,
            "maxConsecutive": 2,
            "startTime": "",
            "endTime": ""
        },
        {
            "id": "staff_1771701066244_5k0ej",
            "name": "蒲池",
            "type": "full",
            "nightShiftType": "all",
            "canOvertime": true,
            "earlyOnly": false,
            "lateOnly": false,
            "monthlyDaysOff": 9,
            "maxDaysPerWeek": 3,
            "maxConsecutive": 2,
            "startTime": "",
            "endTime": ""
        },
        {
            "id": "staff_1771701080136_60aps",
            "name": "武田",
            "type": "full",
            "nightShiftType": "none",
            "canOvertime": true,
            "earlyOnly": false,
            "lateOnly": false,
            "monthlyDaysOff": 9,
            "maxDaysPerWeek": 3,
            "maxConsecutive": 3,
            "startTime": "",
            "endTime": ""
        },
        {
            "id": "staff_1771701096043_lufhg",
            "name": "松藤",
            "type": "full",
            "nightShiftType": "all",
            "canOvertime": true,
            "earlyOnly": false,
            "lateOnly": false,
            "monthlyDaysOff": 9,
            "maxDaysPerWeek": 3,
            "maxConsecutive": 2,
            "startTime": "",
            "endTime": ""
        },
        {
            "id": "staff_1771701110051_f0ngn",
            "name": "坂口",
            "type": "full",
            "nightShiftType": "all",
            "canOvertime": true,
            "earlyOnly": false,
            "lateOnly": false,
            "monthlyDaysOff": 9,
            "maxDaysPerWeek": 3,
            "maxConsecutive": 2,
            "startTime": "",
            "endTime": ""
        },
        {
            "id": "staff_1771701131848_1erh7",
            "name": "桑名",
            "type": "part",
            "nightShiftType": "none",
            "canOvertime": false,
            "earlyOnly": true,
            "lateOnly": false,
            "monthlyDaysOff": 10,
            "maxDaysPerWeek": 5,
            "maxConsecutive": 3,
            "startTime": "07:00",
            "endTime": "16:00"
        },
        {
            "id": "staff_1771701170092_uaju8",
            "name": "小原",
            "type": "part",
            "nightShiftType": "none",
            "canOvertime": false,
            "earlyOnly": false,
            "lateOnly": true,
            "monthlyDaysOff": 10,
            "maxDaysPerWeek": 5,
            "maxConsecutive": 3,
            "startTime": "14:00",
            "endTime": "18:30"
        },
        {
            "id": "staff_1771701219441_stngk",
            "name": "勝田",
            "type": "part",
            "nightShiftType": "none",
            "canOvertime": false,
            "earlyOnly": false,
            "lateOnly": true,
            "monthlyDaysOff": 9,
            "maxDaysPerWeek": 5,
            "maxConsecutive": 4,
            "startTime": "08:30",
            "endTime": "17:30"
        },
        {
            "id": "staff_1771701266582_4zuhj",
            "name": "山口",
            "type": "part",
            "nightShiftType": "none",
            "canOvertime": false,
            "earlyOnly": false,
            "lateOnly": true,
            "monthlyDaysOff": 10,
            "maxDaysPerWeek": 5,
            "maxConsecutive": 2,
            "startTime": "14:00",
            "endTime": "18:00"
        }
    ],
    "schedules": {},
    "exportDate": "2026-02-21T20:50:15.195Z"
}